webhook/__init__.py
webhook/admin.py
webhook/api.py
webhook/apps.py
webhook/base_models.py
webhook/config.py
webhook/handlers.py
webhook/models.py
webhook/utils.py
webhook/contrib/__init__.py
webhook/contrib/drf/__init__.py
webhook/contrib/drf/serializers.py
webhook/management/__init__.py
webhook/management/commands/__init__.py
webhook/management/commands/sync_webhook_events.py
webhook/migrations/0001_initial.py
webhook/migrations/0002_auto_20240202_1148.py
webhook/migrations/0003_auto_20250808_1826.py
webhook/migrations/0004_auto_20250814_1607.py
webhook/migrations/__init__.py
webhook/requester/__init__.py
webhook/requester/base.py
webhook/signals/__init__.py
webhook/signals/handlers.py
bkflow_django_webhook-2.0.0.dist-info/licenses/LICENSE
bkflow_django_webhook-2.0.0.dist-info/WHEEL
bkflow_django_webhook-2.0.0.dist-info/METADATA
bkflow_django_webhook-2.0.0.dist-info/RECORD
