Metadata-Version: 2.4
Name: bkflow-django-webhook
Version: 2.0.0
Summary: A Django app to make it easy for integrating webhook into service.
Author-email: normal-wls <weishi.swee@qq.com>
License-File: LICENSE
Requires-Dist: celery >=5.2.0, <6
Requires-Dist: Django >4.2, <6
Requires-Dist: pyyaml >5, <7
Requires-Dist: pydantic <3
Requires-Dist: pytest >=7.0.1,<8 ; extra == "test"
Requires-Dist: pytest-django>=4.5.2,<5.0 ; extra == "test"
Requires-Dist: djangorestframework >3, <4 ; extra == "test"
Project-URL: Home, https://github.com/TencentBlueKing/bkflow-django-webhook
Provides-Extra: test
